apb_cx_oracle_spatial/__init__.py
apb_cx_oracle_spatial/gestor_oracle.py
apb_cx_oracle_spatial/sdo_geom.py
apb_cx_oracle_spatial-1.1.0.dist-info/METADATA
apb_cx_oracle_spatial-1.1.0.dist-info/WHEEL
apb_cx_oracle_spatial-1.1.0.dist-info/top_level.txt
apb_cx_oracle_spatial-1.1.0.dist-info/RECORD
