Metadata-Version: 2.4
Name: apb_cx_oracle_spatial
Version: 1.1.0
Summary: cx_Oracle with spatial capabilities (SDO_GEOM and OGC)
Home-page: https://github.com/portdebarcelona/PLANOL-generic_python_packages/tree/master/apb_cx_oracle_spatial_pckg
Author: Ernesto Arredondo Martínez
Author-email: ernestone@gmail.com
Maintainer: Port de Barcelona
Maintainer-email: planolport@portdebarcelona.cat
Classifier: Programming Language :: Python :: 3
Classifier: Topic :: Utilities
Classifier: Operating System :: OS Independent
Requires-Python: >=3.6
Requires-Dist: oracledb
Requires-Dist: lxml
Requires-Dist: apb_extra_osgeo_utils<1.2
Requires-Dist: apb_spatial_utils<1.1
Dynamic: author
Dynamic: author-email
Dynamic: classifier
Dynamic: description
Dynamic: home-page
Dynamic: maintainer
Dynamic: maintainer-email
Dynamic: requires-dist
Dynamic: requires-python
Dynamic: summary
